mymath_ghajba.py
mymath_ghajba-0.0.4.dist-info/WHEEL
mymath_ghajba-0.0.4.dist-info/METADATA
mymath_ghajba-0.0.4.dist-info/RECORD
