Metadata-Version: 1.2
Name: mymath_ghajba
Version: 0.0.4
Summary: A simple mathematics module to demonstrate the usage of flit
Home-page: http://www.discoversdk.com/
License: UNKNOWN
Author: GHajba
Author-email: ghajba@gmail.com
Classifier: License :: OSI Approved :: MIT License
